jgrepl/__init__.py
jgrepl/jgrepl.py
jgrepl/repl.py
jgrepl-0.1.5.dist-info/METADATA
jgrepl-0.1.5.dist-info/RECORD
jgrepl-0.1.5.dist-info/WHEEL
jgrepl-0.1.5.dist-info/entry_points.txt
jgrepl-0.1.5.dist-info/top_level.txt
