Metadata-Version: 2.1
Name: jgrepl
Version: 0.1.5
Summary: Extensible command-line REPL for interacting with JSON-graphs containing business objects
Home-page: https://github.com/a115/json-graph-repl
Author: Jordan Dimov
Author-email: jdimov@mlke.net
License: MIT
Keywords: json graph repl cmd2 business
Platform: UNKNOWN
Classifier: Development Status :: 4 - Beta
Classifier: Intended Audience :: Developers
Classifier: Topic :: Software Development
Classifier: Topic :: Scientific/Engineering :: Information Analysis
Classifier: Topic :: Other/Nonlisted Topic
Classifier: License :: OSI Approved :: MIT License
Classifier: Programming Language :: Python :: 3
Classifier: Programming Language :: Python :: 3.6
Requires-Python: >=3
Requires-Dist: Cmd2 (>=0.7.5)
